Metadata-Version: 2.1
Name: trilog
Version: 0.0.0
Summary: Trigonometric and Logarithmic calculators.
Home-page: 
Author: Mudit Bhatnagar
Keywords: calculator
Classifier: Development Status :: 5 - Production/Stable
Classifier: Intended Audience :: Education
Classifier: Operating System :: Microsoft :: Windows :: Windows 10
Classifier: License :: OSI Approved :: MIT License
Classifier: Programming Language :: Python :: 3
License-File: LICENSES.txt
